CHANGES.txt
DESC.txt
LICENSE.txt
MANIFEST.in
README.md
setup.py
PrintDebug.egg-info/PKG-INFO
PrintDebug.egg-info/SOURCES.txt
PrintDebug.egg-info/dependency_links.txt
PrintDebug.egg-info/requires.txt
PrintDebug.egg-info/top_level.txt
docs/README.txt
docs/gpl.txt
printdebug/__init__.py
printdebug/__main__.py
printdebug/catchers.py
printdebug/tools.py
test/__init__.py
test/test_printdebug.py