Metadata-Version: 2.1
Name: PrintDebug
Version: 0.3.5
Summary: A small debug printing module that prints extra info like filenames, function names, and line numbers. It can also recursively print lists, tuples, and dicts.
